jsondiff/__init__.py
jsondiff/_version.py
jsondiff/cli.py
jsondiff/symbols.py
jsondiff-2.2.0.dist-info/LICENSE
jsondiff-2.2.0.dist-info/METADATA
jsondiff-2.2.0.dist-info/WHEEL
jsondiff-2.2.0.dist-info/entry_points.txt
jsondiff-2.2.0.dist-info/top_level.txt
jsondiff-2.2.0.dist-info/RECORD
