Metadata-Version: 2.1
Name: jsondiff
Version: 2.2.0
Summary: Diff JSON and JSON-like structures in Python
Author-email: Zoomer Analytics LLC <eric.reynolds@zoomeranalytics.com>
License: The MIT License (MIT)
Project-URL: Homepage, https://github.com/xlwings/jsondiff
Project-URL: Bug Tracker, https://github.com/xlwings/jsondiff/issues
Keywords: json,diff,diffing,difference,patch,delta,dict,LCS
Classifier: License :: OSI Approved :: MIT License
Classifier: Programming Language :: Python :: 3
Requires-Python: >=3.8
License-File: LICENSE
Requires-Dist: pyyaml
Provides-Extra: dev
Requires-Dist: hypothesis; extra == "dev"
Requires-Dist: pytest; extra == "dev"
Requires-Dist: setuptools-scm; extra == "dev"
Requires-Dist: build; extra == "dev"
